wobbegong/__init__.py
wobbegong/client/__init__.py
wobbegong/client/_base.py
wobbegong/client/client.py
wobbegong/client/readers.py
wobbegong/client/utils.py
wobbegong/core/__init__.py
wobbegong/core/_frame.py
wobbegong/core/_matrix.py
wobbegong/core/_se.py
wobbegong/core/utils.py
wobbegong/core/wobbegongify.py
wobbegong-0.0.5.dist-info/licenses/LICENSE.txt
wobbegong-0.0.5.dist-info/METADATA
wobbegong-0.0.5.dist-info/WHEEL
wobbegong-0.0.5.dist-info/top_level.txt
wobbegong-0.0.5.dist-info/RECORD
