Metadata-Version: 2.4
Name: wobbegong
Version: 0.0.5
Summary: Range-request ready format for Bioconductor objects
Home-page: https://github.com/biocpy/wobbegong
Author: Jayaram Kancherla
Author-email: jayaram.kancherla@gmail.com
License: MIT
Project-URL: Documentation, https://github.com/biocpy/wobbegong
Platform: any
Classifier: Development Status :: 4 - Beta
Classifier: Programming Language :: Python
License-File: LICENSE.txt
Requires-Dist: importlib-metadata; python_version < "3.8"
Requires-Dist: numpy
Requires-Dist: scipy
Requires-Dist: biocframe
Requires-Dist: summarizedexperiment
Requires-Dist: singlecellexperiment
Requires-Dist: requests
Requires-Dist: mattress
Requires-Dist: delayedarray
Requires-Dist: lz4
Provides-Extra: testing
Requires-Dist: setuptools; extra == "testing"
Requires-Dist: pytest; extra == "testing"
Requires-Dist: pytest-cov; extra == "testing"
Dynamic: license-file
